goosebit_forwarded_header/__init__.py
goosebit_forwarded_header/middleware/__init__.py
goosebit_forwarded_header/middleware/forwarded_header.py
goosebit_forwarded_header-0.1.1.dist-info/METADATA
goosebit_forwarded_header-0.1.1.dist-info/WHEEL
goosebit_forwarded_header-0.1.1.dist-info/entry_points.txt
goosebit_forwarded_header-0.1.1.dist-info/RECORD
