Metadata-Version: 2.3
Name: goosebit-forwarded-header
Version: 0.1.1
Summary: gooseBit plugin for Forwarded HTTP header (RFC 7239) support
Author: Ezra Buehler
Author-email: ezra.buehler@husqvarnagroup.com
Requires-Python: >=3.11,<4.0
Classifier: Programming Language :: Python :: 3
Classifier: Programming Language :: Python :: 3.11
Classifier: Programming Language :: Python :: 3.12
Classifier: Programming Language :: Python :: 3.13
Requires-Dist: goosebit
